README.rst
setup.py
NumRep/__init__.py
NumRep/__main__.py
NumRep/funcs.py
NumRep/utils.py
NumRep.egg-info/PKG-INFO
NumRep.egg-info/SOURCES.txt
NumRep.egg-info/dependency_links.txt
NumRep.egg-info/top_level.txt