Metadata-Version: 1.1
Name: NumRep
Version: 0.1.2
Summary: A module to represent numbers by their place value.
Home-page: https://github.com/necessary129/NumRep
Author: Muhammed Shamil K
Author-email: note@noteness.cf
License: 2-clause Simplified BSD
Keywords: number representation order place value denomination
Platform: UNKNOWN
Classifier: Development Status :: 3 - Alpha
Classifier: Environment :: Plugins
Classifier: Intended Audience :: Customer Service
Classifier: Intended Audience :: Developers
Classifier: Operating System :: OS Independent
Classifier: License :: OSI Approved :: BSD License
Classifier: Programming Language :: Python :: 2.7
Classifier: Programming Language :: Python :: 3
Classifier: Programming Language :: Python :: 3.1
Classifier: Programming Language :: Python :: 3.2
Classifier: Programming Language :: Python :: 3.3
Classifier: Programming Language :: Python :: 3.4
Classifier: Topic :: Utilities
